pyuptimerobot2/__init__.py
pyuptimerobot2/client.py
pyuptimerobot2-0.1.2.dist-info/licenses/LICENSE
pyuptimerobot2-0.1.2.dist-info/METADATA
pyuptimerobot2-0.1.2.dist-info/WHEEL
pyuptimerobot2-0.1.2.dist-info/top_level.txt
pyuptimerobot2-0.1.2.dist-info/RECORD
